pypomes_db/__init__.py
pypomes_db/db_common.py
pypomes_db/db_pomes.py
pypomes_db/index_pomes.py
pypomes_db/migration_pomes.py
pypomes_db/mysql_pomes.py
pypomes_db/oracle_pomes.py
pypomes_db/pool_pomes.py
pypomes_db/postgres_pomes.py
pypomes_db/spanner_pomes.py
pypomes_db/sqlserver_pomes.py
pypomes_db/streaming_pomes.py
pypomes_db/sync_pomes.py
pypomes_db/table_pomes.py
pypomes_db/view_pomes.py
pypomes_db-2.8.5.dist-info/METADATA
pypomes_db-2.8.5.dist-info/WHEEL
pypomes_db-2.8.5.dist-info/licenses/LICENSE
pypomes_db-2.8.5.dist-info/RECORD
