Metadata-Version: 2.4
Name: pypomes_db
Version: 2.8.5
Summary: A collection of Python pomes, penyeach (database modules)
Project-URL: Homepage, https://github.com/TheWiseCoder/PyPomes-DB
Project-URL: Bug Tracker, https://github.com/TheWiseCoder/PyPomes-DB/issues
Author-email: GT Nunes <wisecoder01@gmail.com>
License-File: LICENSE
Classifier: License :: OSI Approved :: MIT License
Classifier: Operating System :: OS Independent
Classifier: Programming Language :: Python :: 3
Requires-Python: >=3.14
Requires-Dist: pypomes-core>=2.9.3
